pklue/__init__.py
pklue/korean_utils.py
pklue/pklue.py
pklue/utils.py
pklue-1.0.0.dist-info/METADATA
pklue-1.0.0.dist-info/WHEEL
pklue-1.0.0.dist-info/top_level.txt
pklue-1.0.0.dist-info/RECORD
