Metadata-Version: 2.1
Name: pklue
Version: 1.0.0
Summary: Korean Datasets for Instruction Tuning
Author: Jeongwook Kim
Author-email: k0s1k0s1k0@korea.ac.kr
Requires-Dist: datasets
